aws_cdk/aws_codepipeline_api/_jsii/__init__.py
aws_cdk/aws_codepipeline_api/_jsii/aws-codepipeline-api@0.28.0.jsii.tgz
aws_cdk.aws_codepipeline_api-0.28.0.dist-info/METADATA
aws_cdk.aws_codepipeline_api-0.28.0.dist-info/WHEEL
aws_cdk.aws_codepipeline_api-0.28.0.dist-info/top_level.txt
aws_cdk.aws_codepipeline_api-0.28.0.dist-info/RECORD
