Metadata-Version: 2.1
Name: aws-cdk.aws-codepipeline-api
Version: 0.28.0
Summary: Actions API for AWS Code Pipeline
Home-page: https://github.com/awslabs/aws-cdk
Author: Amazon Web Services
License: UNKNOWN
Project-URL: Source, https://github.com/awslabs/aws-cdk.git
Platform: UNKNOWN
Requires-Python: >=3.6
Requires-Dist: jsii
Requires-Dist: publication (>=0.0.3)
